typewriter_py_nametxt/__about__.py
typewriter_py_nametxt/__init__.py
typewriter_py_nametxt/main.py
typewriter_py_nametxt-1.0.0.dist-info/METADATA
typewriter_py_nametxt-1.0.0.dist-info/WHEEL
typewriter_py_nametxt-1.0.0.dist-info/licenses/LICENSE.txt
typewriter_py_nametxt-1.0.0.dist-info/RECORD
